python3_commons/__init__.py
python3_commons/api_client.py
python3_commons/audit.py
python3_commons/auth.py
python3_commons/cache.py
python3_commons/conf.py
python3_commons/exceptions.py
python3_commons/fs.py
python3_commons/generators.py
python3_commons/helpers.py
python3_commons/object_storage.py
python3_commons/db/__init__.py
python3_commons/db/helpers.py
python3_commons/db/models/__init__.py
python3_commons/db/models/auth.py
python3_commons/db/models/common.py
python3_commons/log/__init__.py
python3_commons/log/filters.py
python3_commons/log/formatters.py
python3_commons/serializers/__init__.py
python3_commons/serializers/common.py
python3_commons/serializers/json.py
python3_commons/serializers/msgpack.py
python3_commons/serializers/msgspec.py
python3_commons-0.14.24.dist-info/licenses/AUTHORS.rst
python3_commons-0.14.24.dist-info/licenses/LICENSE
python3_commons-0.14.24.dist-info/METADATA
python3_commons-0.14.24.dist-info/WHEEL
python3_commons-0.14.24.dist-info/top_level.txt
python3_commons-0.14.24.dist-info/RECORD
