Metadata-Version: 2.4
Name: python3-commons
Version: 0.14.24
Summary: Re-usable Python3 code
Author-email: Oleg Korsak <kamikaze.is.waiting.you@gmail.com>
License-Expression: GPL-3.0
Project-URL: Homepage, https://github.com/kamikaze/python3-commons
Project-URL: Documentation, https://github.com/kamikaze/python3-commons/wiki
Classifier: Development Status :: 4 - Beta
Classifier: Programming Language :: Python
Requires-Python: <3.15.0,>=3.13.9
License-File: LICENSE
License-File: AUTHORS.rst
Requires-Dist: aiobotocore~=3.1.1
Requires-Dist: aiohttp[speedups]<3.15.0,>=3.13.3
Requires-Dist: asyncpg~=0.31.0
Requires-Dist: lxml~=6.0.2
Requires-Dist: msgpack~=1.1.2
Requires-Dist: msgspec==0.20.0
Requires-Dist: pydantic-settings~=2.12.0
Requires-Dist: SQLAlchemy[asyncio]~=2.0.46
Requires-Dist: valkey[libvalkey]~=6.1.1
Requires-Dist: zeep~=4.3.2
Dynamic: license-file
